{
  "id": "119",
  "title": "@流一",
  "type": "cosplay",
  "text": "CP17",
  "summary": "@流一",
  "cover": "/attach/cosplay119/OAQ_3800.jpg",
  "color": "2a3252",
  "click": 0,
  "star": 0,
  "status": 1,
  "created": 1465516800,
  "modified": 1513950649,
  "images": [
    {
      "id": "737",
      "aid": "119",
      "src": "attach/cosplay119/OAQ_3777.jpg",
      "size": "534959",
      "width": "2400",
      "height": "1600",
      "color": "d9d3d6",
      "status": "1",
      "type": "0",
      "created": "1513950648",
      "modified": "1513950648"
    },
    {
      "id": "738",
      "aid": "119",
      "src": "attach/cosplay119/OAQ_3781.jpg",
      "size": "535324",
      "width": "2400",
      "height": "1600",
      "color": "d9d3d4",
      "status": "1",
      "type": "0",
      "created": "1513950648",
      "modified": "1513950648"
    },
    {
      "id": "739",
      "aid": "119",
      "src": "attach/cosplay119/OAQ_3785.jpg",
      "size": "504043",
      "width": "2400",
      "height": "1600",
      "color": "18244e",
      "status": "1",
      "type": "0",
      "created": "1513950648",
      "modified": "1513950648"
    },
    {
      "id": "740",
      "aid": "119",
      "src": "attach/cosplay119/OAQ_3788.jpg",
      "size": "459749",
      "width": "2400",
      "height": "1600",
      "color": "1f244e",
      "status": "1",
      "type": "0",
      "created": "1513950648",
      "modified": "1513950648"
    },
    {
      "id": "741",
      "aid": "119",
      "src": "attach/cosplay119/OAQ_3795.jpg",
      "size": "477278",
      "width": "2400",
      "height": "1600",
      "color": "d4cdcc",
      "status": "1",
      "type": "0",
      "created": "1513950648",
      "modified": "1513950648"
    },
    {
      "id": "742",
      "aid": "119",
      "src": "attach/cosplay119/OAQ_3800.jpg",
      "size": "549411",
      "width": "2400",
      "height": "1600",
      "color": "2a3051",
      "status": "1",
      "type": "0",
      "created": "1513950648",
      "modified": "1513950648"
    }
  ]
}